lnls_ophyd/__init__.py
lnls_ophyd/area_detectors/__init__.py
lnls_ophyd/area_detectors/pilatus_300k.py
lnls_ophyd/detectors_misc/__init__.py
lnls_ophyd/detectors_misc/c400.py
lnls_ophyd/motors/__init__.py
lnls_ophyd-1.0.0.dist-info/METADATA
lnls_ophyd-1.0.0.dist-info/WHEEL
lnls_ophyd-1.0.0.dist-info/top_level.txt
lnls_ophyd-1.0.0.dist-info/RECORD
